geniml/__init__.py
geniml/_version.py
geniml/cli.py
geniml/const.py
geniml/exceptions.py
geniml/utils.py
geniml/assess/__init__.py
geniml/assess/assess.py
geniml/assess/cli.py
geniml/assess/distance.py
geniml/assess/intersection.py
geniml/assess/likelihood.py
geniml/assess/utils.py
geniml/atacformer/__init__.py
geniml/atacformer/_version.py
geniml/atacformer/configuration_atacformer.py
geniml/atacformer/data_processing.py
geniml/atacformer/functional.py
geniml/atacformer/modeling_atacformer.py
geniml/atacformer/modeling_utils.py
geniml/atacformer/training_utils.py
geniml/bbclient/__init__.py
geniml/bbclient/bbclient.py
geniml/bbclient/cli.py
geniml/bbclient/const.py
geniml/bbclient/utils.py
geniml/bedshift/__init__.py
geniml/bedshift/_version.py
geniml/bedshift/bedshift.py
geniml/bedshift/cli.py
geniml/bedshift/const.py
geniml/bedshift/yaml_handler.py
geniml/bedspace/__init__.py
geniml/bedspace/_version.py
geniml/bedspace/argparsers.py
geniml/bedspace/cli.py
geniml/bedspace/const.py
geniml/bedspace/distances.py
geniml/bedspace/helpers.py
geniml/bedspace/preprocess.py
geniml/bedspace/search.py
geniml/bedspace/train.py
geniml/bedspace/visualization.py
geniml/craft/__init__.py
geniml/craft/_version.py
geniml/craft/configuration_craft.py
geniml/craft/modeling_craft.py
geniml/craft/training_utils.py
geniml/eval/__init__.py
geniml/eval/cli.py
geniml/eval/const.py
geniml/eval/ctt.py
geniml/eval/gdst.py
geniml/eval/npt.py
geniml/eval/rct.py
geniml/eval/utils.py
geniml/geneformer/__init__.py
geniml/geneformer/_version.py
geniml/geneformer/configuration_geneformer.py
geniml/geneformer/modeling_geneformer.py
geniml/geneformer/tokenization_geneformer.py
geniml/io/__init__.py
geniml/io/const.py
geniml/io/exceptions.py
geniml/io/io.py
geniml/io/utils.py
geniml/likelihood/__init__.py
geniml/likelihood/build_model.py
geniml/likelihood/cli.py
geniml/models/__init__.py
geniml/models/main.py
geniml/nn/__init__.py
geniml/nn/main.py
geniml/region2vec/__init__.py
geniml-0.8.4.dist-info/licenses/LICENSE.txt
geniml-0.8.4.dist-info/METADATA
geniml-0.8.4.dist-info/WHEEL
geniml-0.8.4.dist-info/entry_points.txt
geniml-0.8.4.dist-info/top_level.txt
geniml-0.8.4.dist-info/RECORD
